crate2bib-0.7.1.dist-info/METADATA
crate2bib-0.7.1.dist-info/WHEEL
crate2bib/__init__.py
crate2bib/__init__.pyi
crate2bib/ffi.py
crate2bib/libcrate2bib.so
crate2bib/py.typed
crate2bib-0.7.1.dist-info/RECORD
